lipad.py
lipad_sdk-1.0.5.dist-info/METADATA
lipad_sdk-1.0.5.dist-info/WHEEL
lipad_sdk-1.0.5.dist-info/top_level.txt
lipad_sdk-1.0.5.dist-info/RECORD
