Metadata-Version: 2.1
Name: lipad_sdk
Version: 1.0.5
Summary: Provides Direct API and Checkout methods for Lipad
Author: Timothy Waweru
Classifier: Programming Language :: Python :: 3
Classifier: License :: OSI Approved :: MIT License
Classifier: Operating System :: OS Independent
Requires-Python: >=3.6
Requires-Dist: aiohttp
Requires-Dist: pycryptodome
Requires-Dist: requests
